fpp_sle/__init__.py
fpp_sle/__main__.py
fpp_sle/fpp/__init__.py
fpp_sle/fpp/forcing_generators.py
fpp_sle/fpp/get_arrival_times.py
fpp_sle/sde/__init__.py
fpp_sle/sde/runge_kutta_sde.py
fpp_sle-0.3.0.dist-info/LICENSE
fpp_sle-0.3.0.dist-info/METADATA
fpp_sle-0.3.0.dist-info/WHEEL
fpp_sle-0.3.0.dist-info/RECORD
