Metadata-Version: 2.1
Name: fpp-sle
Version: 0.3.0
Summary: Implements FPP and SLE algorithms
License: GPL-3.0-or-later
Author: engeir
Author-email: engeir@pm.me
Requires-Python: >=3.8,<3.13
Classifier: Development Status :: 4 - Beta
Classifier: Intended Audience :: Education
Classifier: Intended Audience :: Science/Research
Classifier: License :: OSI Approved :: GNU General Public License v3 or later (GPLv3+)
Classifier: Programming Language :: Python :: 3
Classifier: Programming Language :: Python :: 3.8
Classifier: Programming Language :: Python :: 3.9
Classifier: Programming Language :: Python :: 3.10
Classifier: Programming Language :: Python :: 3.11
Classifier: Programming Language :: Python :: 3.12
Classifier: Topic :: Scientific/Engineering :: Physics
Requires-Dist: importlib-metadata (>=5,<7)
Requires-Dist: numba (>=0.53.1,<0.59.0)
Requires-Dist: numpy (>=1.20.2,<2.0.0)
Requires-Dist: superposed-pulses (>=1.2,<2.0)
